examples/__init__.py
swarm/__init__.py
swarm/core.py
swarm/types.py
swarm/util.py
swarm/repl/__init__.py
swarm/repl/repl.py
tests/__init__.py
tests/mock_client.py
tests/test_core.py
tests/test_util.py
aihive-0.1.0.dist-info/LICENSE
aihive-0.1.0.dist-info/METADATA
aihive-0.1.0.dist-info/WHEEL
aihive-0.1.0.dist-info/top_level.txt
aihive-0.1.0.dist-info/zip-safe
aihive-0.1.0.dist-info/RECORD
