Metadata-Version: 2.1
Name: aihive
Version: 0.1.0
Summary: A multi-agent orchestration framework.
Author: Jacob Weiss
License: MIT
Requires-Python: >=3.10
License-File: LICENSE
Requires-Dist: numpy
Requires-Dist: openai >=1.33.0
Requires-Dist: pytest
Requires-Dist: requests
Requires-Dist: tqdm
Requires-Dist: pre-commit
Requires-Dist: instructor
